{
  "type": "Feature",
  "properties": {
    "gn:gn_country":"GU",
    "gn:gn_fcode":"PPL",
    "gn:gn_pop":2592,
    "gn:population":2853,
    "iso:country":"GU",
    "name:ceb_x_preferred":[
        "Sinajana Village"
    ],
    "name:cha_x_preferred":[
        "Sinah\u00e5\u00f1a"
    ],
    "name:eng_x_preferred":[
        "Sinajana"
    ],
    "name:fas_x_preferred":[
        "\u0633\u06cc\u0646\u0627\u062c\u0627\u0646\u0627"
    ],
    "name:fra_x_preferred":[
        "Sinajana"
    ],
    "name:ita_x_preferred":[
        "Sinajana"
    ],
    "name:jpn_x_preferred":[
        "\u30b7\u30ca\u30cf\u30cb\u30e3"
    ],
    "name:nld_x_preferred":[
        "Sinajana"
    ],
    "name:pol_x_preferred":[
        "Sinajana"
    ],
    "name:spa_x_preferred":[
        "Sinajana"
    ],
    "name:swe_x_preferred":[
        "Sinajana Village"
    ],
    "name:swe_x_variant":[
        "Sinajana"
    ],
    "name:unk_x_variant":[
        "Sinahanna"
    ],
    "name:urd_x_preferred":[
        "\u0633\u06cc\u0646\u0627\u062c\u0627\u0646\u0627\u060c \u06af\u0648\u0627\u0645"
    ],
    "name:urd_x_variant":[
        "\u0633\u06cc\u0646\u0627\u062c\u0627\u0646\u0627"
    ],
    "name:war_x_preferred":[
        "Sinajana"
    ],
    "qs_pg:aaroncc":"GU",
    "qs_pg:gn_country":"GU",
    "qs_pg:gn_fcode":"PPL",
    "qs_pg:gn_pop":2592,
    "qs_pg:name":"Sinajana Village",
    "qs_pg:photos_9r":0,
    "qs_pg:photos_sr":0,
    "qs_pg:pop_sr":4,
    "qs_pg:qs_pg_placetype":"locality",
    "wof:name":"Sinajana Village",
    "wof:placetype":"locality",
    "wof:population":2853
},
  "geometry": {"coordinates":[144.75406000000001,13.46334],"type":"Point"}
}