{
  "type": "Feature",
  "properties": {
    "iso:country":"GU",
    "name:ces_x_preferred":[
        "Andersenova leteck\u00e1 z\u00e1kladna"
    ],
    "name:deu_x_preferred":[
        "Andersen Air Force Base"
    ],
    "name:eng_x_preferred":[
        "Andersen Air Force Base"
    ],
    "name:eng_x_variant":[
        "UAM",
        "PGUA"
    ],
    "name:fas_x_preferred":[
        "\u067e\u0627\u06cc\u06af\u0627\u0647 \u0646\u06cc\u0631\u0648\u06cc \u0647\u0648\u0627\u06cc\u06cc \u0627\u0646\u062f\u0631\u0633\u0646"
    ],
    "name:fin_x_preferred":[
        "Andersenin lentotukikohta"
    ],
    "name:fra_x_preferred":[
        "Andersen Air Force Base"
    ],
    "name:ita_x_preferred":[
        "Andersen Air Force Base"
    ],
    "name:jpn_x_preferred":[
        "\u30a2\u30f3\u30c0\u30fc\u30bb\u30f3\u7a7a\u8ecd\u57fa\u5730"
    ],
    "name:kor_x_preferred":[
        "\uc564\ub354\uc2a8 \uacf5\uad70\uae30\uc9c0"
    ],
    "name:msa_x_preferred":[
        "Pangkalan Udara Andersen"
    ],
    "name:nld_x_preferred":[
        "Andersen Air Force Base"
    ],
    "name:nob_x_preferred":[
        "Andersen Air Force Base"
    ],
    "name:pol_x_preferred":[
        "Port lotniczy Andersen"
    ],
    "name:rus_x_preferred":[
        "\u0410\u043d\u0434\u0435\u0440\u0441\u0435\u043d"
    ],
    "name:spa_x_preferred":[
        "Base de la Fuerza A\u00e9rea Andersen"
    ],
    "name:swe_x_preferred":[
        "USAF Andersen Air Force Base"
    ],
    "name:tgk_x_preferred":[
        "\u041f\u043e\u0439\u0433\u043e\u04b3\u0438 \u041d\u0435\u0440\u04ef\u0438 \u04b2\u0430\u0432\u043e\u0438\u0438 \u0410\u043d\u0434\u0435\u0440\u0441\u0435\u043d"
    ],
    "name:zho_x_preferred":[
        "\u5b89\u5fb7\u68ee\u7a7a\u519b\u57fa\u5730"
    ],
    "oa:elevation_ft":"627",
    "oa:type":"medium_airport",
    "wd:wordcount":3418,
    "woe:hierarchy":{
        "country_id":23424832,
        "planet_id":1,
        "state_id":24549725
    },
    "wof:name":"Anderson Air Force Base",
    "wof:placetype":"campus"
},
  "geometry": {"coordinates":[144.929993,13.584],"type":"Point"}
}