{
  "type": "Feature",
  "properties": {
    "gn:country":"GU",
    "gn:fcode":"PPL",
    "gn:population":6825,
    "iso:country":"GU",
    "qs_pg:aaroncc":"GU",
    "qs_pg:gn_country":"GU",
    "qs_pg:gn_fcode":"PPL",
    "qs_pg:gn_pop":6825,
    "qs_pg:name":"Mongmong-Toto-Maite Village",
    "qs_pg:photos_9r":0,
    "qs_pg:photos_sr":0,
    "qs_pg:pop_sr":5,
    "qs_pg:qs_pg_placetype":"locality",
    "wof:name":"Mongmong-Toto-Maite Village",
    "wof:placetype":"locality",
    "wof:population":6825
},
  "geometry": {"coordinates":[144.78214,13.46857],"type":"Point"}
}